qcodes_contrib_drivers/__init__.py
qcodes_contrib_drivers/_version.py
qcodes_contrib_drivers/drivers/CMTS5048.py
qcodes_contrib_drivers/drivers/__init__.py
qcodes_contrib_drivers/drivers/Advantech/PCIE_1751.py
qcodes_contrib_drivers/drivers/Advantech/__init__.py
qcodes_contrib_drivers/drivers/Agilent/Agilent_N9000A.py
qcodes_contrib_drivers/drivers/Agilent/__init__.py
qcodes_contrib_drivers/drivers/AimTTi/EL320P.py
qcodes_contrib_drivers/drivers/AimTTi/__init__.py
qcodes_contrib_drivers/drivers/Ametek/SR_7270.py
qcodes_contrib_drivers/drivers/Ametek/__init__.py
qcodes_contrib_drivers/drivers/Andor/DU401.py
qcodes_contrib_drivers/drivers/Andor/__init__.py
qcodes_contrib_drivers/drivers/Attocube/ANC300.py
qcodes_contrib_drivers/drivers/Attocube/ANC300sim.py
qcodes_contrib_drivers/drivers/Attocube/ANC350.py
qcodes_contrib_drivers/drivers/Attocube/__init__.py
qcodes_contrib_drivers/drivers/Attocube/ANC350Lib/__init__.py
qcodes_contrib_drivers/drivers/Attocube/ANC350Lib/interface.py
qcodes_contrib_drivers/drivers/Attocube/ANC350Lib/v3.py
qcodes_contrib_drivers/drivers/Attocube/ANC350Lib/v4.py
qcodes_contrib_drivers/drivers/Aviosys/IP_Power_9258S.py
qcodes_contrib_drivers/drivers/Aviosys/__init__.py
qcodes_contrib_drivers/drivers/Bilt/ITest.py
qcodes_contrib_drivers/drivers/Bilt/__init__.py
qcodes_contrib_drivers/drivers/BlueFors/BlueFors.py
qcodes_contrib_drivers/drivers/BlueFors/__init__.py
qcodes_contrib_drivers/drivers/CopperMountain/M5180.py
qcodes_contrib_drivers/drivers/CopperMountain/S5048.py
qcodes_contrib_drivers/drivers/CopperMountain/__init__.py
qcodes_contrib_drivers/drivers/Cryocon/__init__.py
qcodes_contrib_drivers/drivers/Cryocon/cryocon_26.py
qcodes_contrib_drivers/drivers/Cryogenic/CryogenicSMS120C.py
qcodes_contrib_drivers/drivers/Cryogenic/__init__.py
qcodes_contrib_drivers/drivers/DaylightSolutions/MIRcat.py
qcodes_contrib_drivers/drivers/DaylightSolutions/__init__.py
qcodes_contrib_drivers/drivers/ERAInstruments/__init__.py
qcodes_contrib_drivers-0.22.0.dist-info/LICENSE
qcodes_contrib_drivers-0.22.0.dist-info/LICENSE_TEKTRONIX_AWG520_KEITHLEY_2700
qcodes_contrib_drivers-0.22.0.dist-info/METADATA
qcodes_contrib_drivers-0.22.0.dist-info/WHEEL
qcodes_contrib_drivers-0.22.0.dist-info/top_level.txt
qcodes_contrib_drivers-0.22.0.dist-info/RECORD
