Metadata-Version: 2.1
Name: qcodes_contrib_drivers
Version: 0.22.0
Summary: User contributed drivers for QCoDeS
Maintainer-email: QCoDeS Community <qcodes-support@microsoft.com>
License: MIT
Project-URL: Homepage, https://github.com/QCoDeS/Qcodes_contrib_drivers
Project-URL: Documentation, https://qcodes.github.io/Qcodes_contrib_drivers/
Project-URL: Source, https://github.com/qcodes/qcodes_contrib_drivers
Project-URL: Tracker, https://github.com/QCoDeS/Qcodes_contrib_drivers/issues
Classifier: Development Status :: 3 - Alpha
Classifier: Intended Audience :: Science/Research
Classifier: License :: OSI Approved :: MIT License
Classifier: License :: OSI Approved :: GNU General Public License v2 or later (GPLv2+)
Classifier: Programming Language :: Python :: 3 :: Only
Classifier: Programming Language :: Python :: 3.9
Classifier: Programming Language :: Python :: 3.10
Classifier: Programming Language :: Python :: 3.11
Classifier: Programming Language :: Python :: 3.12
Classifier: Topic :: Scientific/Engineering
Requires-Python: >=3.9
License-File: LICENSE_TEKTRONIX_AWG520_KEITHLEY_2700
License-File: LICENSE
Requires-Dist: qcodes >=0.42.0
Requires-Dist: versioningit >=2.2.1
Requires-Dist: packaging
Requires-Dist: pandas
Requires-Dist: cffi
Provides-Extra: docs
Requires-Dist: sphinx ; extra == 'docs'
Requires-Dist: sphinx-rtd-theme ; extra == 'docs'
Requires-Dist: nbsphinx ; extra == 'docs'
Provides-Extra: test
Requires-Dist: pytest >=6.2.2 ; extra == 'test'
Requires-Dist: pytest-mock ; extra == 'test'
Requires-Dist: mypy >=0.940 ; extra == 'test'
Requires-Dist: pytest-cov >=3.0.0 ; extra == 'test'
Requires-Dist: coverage[toml] >=6.2 ; extra == 'test'
Requires-Dist: pyvisa-sim ; extra == 'test'
Requires-Dist: types-tqdm >=4.64.6 ; extra == 'test'
Requires-Dist: pandas-stubs ; extra == 'test'
